README.md
setup.cfg
setup.py
mudslide/__init__.py
mudslide/__main__.py
mudslide/batch.py
mudslide/cumulative_sh.py
mudslide/ehrenfest.py
mudslide/electronics.py
mudslide/even_sampling.py
mudslide/exceptions.py
mudslide/integration.py
mudslide/math.py
mudslide/models.py
mudslide/propagation.py
mudslide/surface.py
mudslide/tracer.py
mudslide/trajectory_sh.py
mudslide/typing.py
mudslide/version.py
mudslide.egg-info/PKG-INFO
mudslide.egg-info/SOURCES.txt
mudslide.egg-info/dependency_links.txt
mudslide.egg-info/entry_points.txt
mudslide.egg-info/requires.txt
mudslide.egg-info/top_level.txt
test/test_mains.py
test/test_math.py
test/test_quadrature.py